NEMO_periodic_table_question/__init__.py
NEMO_periodic_table_question/apps.py
NEMO_periodic_table_question/periodic_table_question.py
NEMO_periodic_table_question/static/NEMO_periodic_table_question/periodic_table.css
NEMO_periodic_table_question/templates/NEMO_periodic_table_question/periodic_table.html
nemo_periodic_table_question-2.1.1.dist-info/licenses/LICENSE
nemo_periodic_table_question-2.1.1.dist-info/METADATA
nemo_periodic_table_question-2.1.1.dist-info/WHEEL
nemo_periodic_table_question-2.1.1.dist-info/top_level.txt
nemo_periodic_table_question-2.1.1.dist-info/RECORD
