Metadata-Version: 2.4
Name: NEMO-periodic-table-question
Version: 2.1.1
Summary: Install Periodic table question plugin for NEMO
Author-email: Atlantis Labs LLC <atlantis@atlantislabs.io>
License: MIT
Project-URL: Homepage, https://gitlab.com/nemo-community/atlantis-labs/nemo-periodic-table-question
Project-URL: Changelog, https://gitlab.com/nemo-community/atlantis-labs/nemo-periodic-table-question/-/releases
Project-URL: Issues, https://gitlab.com/nemo-community/atlantis-labs/nemo-periodic-table-question/-/issues
Project-URL: CI, https://gitlab.com/nemo-community/atlantis-labs/nemo-periodic-table-question/-/pipelines
Keywords: NEMO
Classifier: Development Status :: 5 - Production/Stable
Classifier: Intended Audience :: Developers
Classifier: License :: OSI Approved :: MIT License
Classifier: Programming Language :: Python :: 3.9
Classifier: Programming Language :: Python :: 3.10
Classifier: Programming Language :: Python :: 3.11
Classifier: Programming Language :: Python :: 3.12
Classifier: Programming Language :: Python :: 3.13
Requires-Python: >=3.9
License-File: LICENSE
Requires-Dist: django
Provides-Extra: nemo-ce
Requires-Dist: NEMO-CE>=7.0.0; extra == "nemo-ce"
Provides-Extra: nemo
Requires-Dist: NEMO>=7.0.0; extra == "nemo"
Provides-Extra: dev-tools
Requires-Dist: pre-commit; extra == "dev-tools"
Requires-Dist: djlint; extra == "dev-tools"
Requires-Dist: black; extra == "dev-tools"
Dynamic: license-file
